LICENSE.txt
README.md
setup.cfg
setup.py
fn_python_utils/VERSION.txt
fn_python_utils/__init__.py
fn_python_utils/display.py
fn_python_utils/io.py
fn_python_utils/memoize.py
fn_python_utils/singleton.py
fn_python_utils/timer.py
fn_python_utils.egg-info/PKG-INFO
fn_python_utils.egg-info/SOURCES.txt
fn_python_utils.egg-info/dependency_links.txt
fn_python_utils.egg-info/requires.txt
fn_python_utils.egg-info/top_level.txt
tests/test_display.py